mfd_packet_capture/__init__.py
mfd_packet_capture/exceptions.py
mfd_packet_capture/pktcap.py
mfd_packet_capture/tcpdump.py
mfd_packet_capture/tshark.py
mfd_packet_capture-2.16.0.dist-info/licenses/AUTHORS.md
mfd_packet_capture-2.16.0.dist-info/licenses/LICENSE.md
mfd_packet_capture-2.16.0.dist-info/METADATA
mfd_packet_capture-2.16.0.dist-info/WHEEL
mfd_packet_capture-2.16.0.dist-info/top_level.txt
mfd_packet_capture-2.16.0.dist-info/RECORD
