Metadata-Version: 2.4
Name: mfd-packet-capture
Version: 2.16.0
Summary: Module for Packet Capture support. Within the module, there are wrappers written for tcpdump, tshark & pktcap tools.
Project-URL: Homepage, https://github.com/intel/mfd
Project-URL: Repository, https://github.com/intel/mfd-packet-capture
Project-URL: Issues, https://github.com/intel/mfd-packet-capture/issues
Project-URL: Changelog, https://github.com/intel/mfd-packet-capture/blob/main/CHANGELOG.md
Requires-Python: <3.14,>=3.10
License-File: LICENSE.md
License-File: AUTHORS.md
Requires-Dist: mfd-base-tool<3,>=2.7.0
Requires-Dist: mfd-typing<2,>=1.23.0
Requires-Dist: mfd-common-libs<2,>=1.11.0
Requires-Dist: mfd_kernel_namespace<2,>=1.8.0
Dynamic: license-file
